unityparser/__init__.py
unityparser/commands.py
unityparser/composer.py
unityparser/constants.py
unityparser/constructor.py
unityparser/dumper.py
unityparser/emitter.py
unityparser/errors.py
unityparser/loader.py
unityparser/parser.py
unityparser/register.py
unityparser/representer.py
unityparser/resolver.py
unityparser/scanner.py
unityparser/serializer.py
unityparser/utils.py
unityparser-4.0.0.dist-info/AUTHORS
unityparser-4.0.0.dist-info/LICENSE
unityparser-4.0.0.dist-info/METADATA
unityparser-4.0.0.dist-info/WHEEL
unityparser-4.0.0.dist-info/top_level.txt
unityparser-4.0.0.dist-info/RECORD
