Metadata-Version: 2.1
Name: unityparser
Version: 4.0.0
Summary: A python library to parse and dump Unity YAML files
Home-page: https://github.com/socialpoint-labs/unity-yaml-parser
Author: Ricard Valverde
Author-email: ricard.valverde@socialpoint.es
License: MIT License
Keywords: unity,yaml,parser,serializer
Platform: UNKNOWN
Classifier: Programming Language :: Python :: 3
Classifier: Programming Language :: Python :: 3 :: Only
Classifier: License :: OSI Approved :: MIT License
Classifier: Operating System :: OS Independent
Classifier: Development Status :: 3 - Alpha
Classifier: Intended Audience :: Developers
Classifier: Topic :: Software Development :: Libraries :: Python Modules
Requires-Python: >=3.7.0
License-File: LICENSE
License-File: AUTHORS
Requires-Dist: PyYAML (==6.0.1)
Provides-Extra: development
Requires-Dist: pip-compile-multi ; extra == 'development'
Requires-Dist: pytest ; extra == 'development'
Requires-Dist: pytest-cov ; extra == 'development'
Requires-Dist: tox ; extra == 'development'
Requires-Dist: tox-conda ; extra == 'development'
